mcp_extent/__init__.py
mcp_extent/models.py
mcp_extent/server.py
mcp_extent/parsers/__init__.py
mcp_extent/parsers/base.py
mcp_extent/parsers/html_parser.py
mcp_extent/parsers/json_parser.py
mcp_extent/transformers/__init__.py
mcp_extent/transformers/llm_transformer.py
mcp_extent-0.1.1.dist-info/METADATA
mcp_extent-0.1.1.dist-info/WHEEL
mcp_extent-0.1.1.dist-info/entry_points.txt
mcp_extent-0.1.1.dist-info/licenses/LICENSE
mcp_extent-0.1.1.dist-info/RECORD
